terrachecker/__init__.py
terrachecker/terrachecker.py
terrachecker/terraform_checker.py
terrachecker-0.0.4.data/data/LICENSE.txt
terrachecker-0.0.4.dist-info/DESCRIPTION.rst
terrachecker-0.0.4.dist-info/METADATA
terrachecker-0.0.4.dist-info/RECORD
terrachecker-0.0.4.dist-info/WHEEL
terrachecker-0.0.4.dist-info/entry_points.txt
terrachecker-0.0.4.dist-info/metadata.json
terrachecker-0.0.4.dist-info/top_level.txt
tests/__init__.py
tests/test_terraform_checker.py
